hybridoma/__init__.py
hybridoma/hybridoma.py
hybridoma/quart.py
hybridoma/static/hybridoma.js.txt
hybridoma/static/lucide.min.js.txt
hybridoma/static/morphdom.min.js.txt
hybridoma/static/pico.min.css
hybridoma-0.3.3.dist-info/licenses/LICENSE
hybridoma-0.3.3.dist-info/METADATA
hybridoma-0.3.3.dist-info/WHEEL
hybridoma-0.3.3.dist-info/top_level.txt
hybridoma-0.3.3.dist-info/RECORD
