Metadata-Version: 2.4
Name: hybridoma
Version: 0.3.3
Summary: Write Python, get a reactive frontend - no JS framework required
Author-email: uukelele <robustrobot11@gmail.com>
License: MIT License
Classifier: Programming Language :: Python :: 3
Classifier: License :: OSI Approved :: MIT License
Classifier: Operating System :: OS Independent
Classifier: Topic :: Internet :: WWW/HTTP :: Dynamic Content
Requires-Python: >=3.10
License-File: LICENSE
Requires-Dist: Quart>=0.20.0
Requires-Dist: flask-sqlalchemy
Requires-Dist: minify-html
Requires-Dist: quart-flask-patch
Requires-Dist: markupsafe
Dynamic: license-file
